qlibx/__init__.py
qlibx/qlibx.py
qlibx-1.0.3.dist-info/licenses/License.txt
qlibx-1.0.3.dist-info/METADATA
qlibx-1.0.3.dist-info/WHEEL
qlibx-1.0.3.dist-info/top_level.txt
qlibx-1.0.3.dist-info/RECORD
