Metadata-Version: 2.4
Name: qlibx
Version: 1.0.3
Summary: A lightweight quantum computing library for foundational tools and mathematical operations.
Home-page: https://github.com/Suraj52721/qc_lib/tree/master
Author: Suraj Singh
Author-email: Suraj Singh <suraj.52721@gmail.com>
License: MIT License
Classifier: Programming Language :: Python :: 3
Classifier: License :: OSI Approved :: MIT License
Classifier: Operating System :: OS Independent
Classifier: Intended Audience :: Science/Research
Classifier: Topic :: Scientific/Engineering :: Physics
Requires-Python: >=3.7
License-File: License.txt
Requires-Dist: numpy>=1.21.0
Dynamic: author
Dynamic: home-page
Dynamic: license-file
Dynamic: requires-python
